torchy/__init__.py
torchy/layer.py
torchy/loss.py
torchy/optim.py
torchy/scheduler.py
torchy/sequential.py
torchy/tools.py
torchy/value.py
torchy/data/__init__.py
torchy/data/data.py
torchy/nn/__init__.py
torchy/nn/initializations/__init__.py
torchy/nn/initializations/init.py
torchy/nn/modules/__init__.py
torchy/nn/modules/activation.py
torchy/nn/modules/batchnorm.py
torchy/nn/modules/conv.py
torchy/nn/modules/dense.py
torchy/nn/modules/dropout.py
torchy/nn/modules/embedding.py
torchy/nn/modules/loss.py
torchy/nn/modules/module.py
torchy/nn/modules/pooling.py
torchy/nn/modules/rnn.py
torchy/nn/modules/sequential.py
torchy/nn/values/__init__.py
torchy/nn/values/value.py
torchy/optimizers/__init__.py
torchy/optimizers/optim.py
torchy/optimizers/scheduler.py
torchy_nn-0.3.5.3.dist-info/METADATA
torchy_nn-0.3.5.3.dist-info/WHEEL
torchy_nn-0.3.5.3.dist-info/top_level.txt
torchy_nn-0.3.5.3.dist-info/RECORD
